dracoon/__init__.py
dracoon/branding/__init__.py
dracoon/branding/models.py
dracoon/branding/responses.py
dracoon/client/__init__.py
dracoon/client/models.py
dracoon/config/__init__.py
dracoon/config/responses.py
dracoon/crypto/__init__.py
dracoon/crypto/models.py
dracoon/downloads/__init__.py
dracoon/errors/__init__.py
dracoon/eventlog/__init__.py
dracoon/eventlog/responses.py
dracoon/groups/__init__.py
dracoon/groups/models.py
dracoon/groups/responses.py
dracoon/logger.py
dracoon/nodes/__init__.py
dracoon/nodes/models.py
dracoon/nodes/responses.py
dracoon/public/__init__.py
dracoon/public/models.py
dracoon/public/responses.py
dracoon/reports/__init__.py
dracoon/reports/models.py
dracoon/reports/responses.py
dracoon/roles/__init__.py
dracoon/roles/models.py
dracoon/roles/responses.py
dracoon/settings/__init__.py
dracoon/settings/models.py
dracoon/settings/responses.py
dracoon/shares/__init__.py
dracoon/shares/models.py
dracoon/shares/responses.py
dracoon/uploads/__init__.py
dracoon/uploads/models.py
dracoon/user/__init__.py
dracoon/user/models.py
dracoon/user/responses.py
dracoon/users/__init__.py
dracoon/users/models.py
dracoon-1.13.0.dist-info/LICENSE
dracoon-1.13.0.dist-info/METADATA
dracoon-1.13.0.dist-info/WHEEL
dracoon-1.13.0.dist-info/RECORD
