Metadata-Version: 2.1
Name: dracoon
Version: 1.13.0
Summary: DRACOON API wrapper in Python
License: MIT
Author: Octavio Simone
Author-email: o.simone@dracoon.com
Requires-Python: >=3.10,<4.0
Classifier: License :: OSI Approved :: MIT License
Classifier: Programming Language :: Python :: 3
Classifier: Programming Language :: Python :: 3.10
Classifier: Programming Language :: Python :: 3.11
Classifier: Programming Language :: Python :: 3.12
Requires-Dist: asyncio (>=3.4.3,<4.0.0)
Requires-Dist: cryptography (>=42.0.5,<43.0.0)
Requires-Dist: httpx (>=0.27.0,<0.28.0)
Requires-Dist: pydantic (>=2.6.3,<3.0.0)
Requires-Dist: tenacity (>=8.2.3,<9.0.0)
